cqu_cj/__init__.py
cqu_cj/__main__.py
cqu_cj/utils.py
cqu_cj/version.py
cqu_cj/config/__init__.py
cqu_cj/config/config.py
cqu_cj/config/config_default.yaml
cqu_cj-0.1.4.dist-info/LICENSE
cqu_cj-0.1.4.dist-info/METADATA
cqu_cj-0.1.4.dist-info/WHEEL
cqu_cj-0.1.4.dist-info/entry_points.txt
cqu_cj-0.1.4.dist-info/top_level.txt
cqu_cj-0.1.4.dist-info/RECORD
