Metadata-Version: 2.1
Name: cqu-cj
Version: 0.1.4
Summary: 第三方重庆大学成绩查询工具
Home-page: https://github.com/CQU-AI/cqu-cj
Author: CQU-AI
Author-email: peter@mail.loopy.tech
License: GPL License
Platform: all
Requires-Python: >=3.6
Requires-Dist: pandas (>=1.1.1)
Requires-Dist: requests (>=2.24.0)
Requires-Dist: lxml (>=4.5.2)
